client/__init__.py
client/client.py
client/client/__init__.py
client/client/add_contact.py
client/client/database.py
client/client/del_contact.py
client/client/main_window.py
client/client/main_window_conv.py
client/client/start_dialog.py
client/client/transport.py
client/common/__init__.py
client/common/decorator.py
client/common/descryptors.py
client/common/errors.py
client/common/metaclasses.py
client/common/utils.py
client/common/variables.py
client/unit_tests/__init__.py
client/unit_tests/test_client.py
client/unit_tests/test_utils.py
ng_client-1.0.0.dist-info/METADATA
ng_client-1.0.0.dist-info/WHEEL
ng_client-1.0.0.dist-info/top_level.txt
ng_client-1.0.0.dist-info/RECORD
